opencnpj/__init__.py
opencnpj/exceptions.py
opencnpj/model.py
opencnpj/wrapper.py
opencnpj-0.0.3.dist-info/licenses/LICENSE
opencnpj-0.0.3.dist-info/METADATA
opencnpj-0.0.3.dist-info/WHEEL
opencnpj-0.0.3.dist-info/top_level.txt
opencnpj-0.0.3.dist-info/RECORD
